[
    {
        "id": "0",
        "name": "Informationsläckage",
        "time": "2",
        "imageUrl": "ivan.svg",
        "backgroundColor": "#E2E7EE",
        "age": "3-6",
        "content": [
            {
                "title": "Vad är informationsläckage?",
                "text": "Informationsläckage är ett exempel där personlig eller känslig information hamnar i fel händer, oftast beroende på brist på säkerhet eller okunskap. Barnen är särskilt utsatta när de används tillsammans med internet, samtidigt som många föräldrar och lärare dåligt är förberedda att beskydda dem. Även om många föräldrar är medvetna om faror som online finns, använder bara hälften redskap som föräldrakontroller för att skydda sina barn."
            },
            {
                "text": "Skolor har en viktig funktion i att öka cybersäkerhetsmedvetenheten, men resurser och struktur för detta saknas vanligtvis. Utan rätt ledning riskerar barn att dela känslig information som kan utnyttjas av andra. Många barn utsätts för olämpligt innehåll eller kontakta med främlingar. Avgörande är det därför att vuxna tar ansvar för att bepröva barnens digitala trygghet."
            },
            {
                "imageWithText": {
                    "text": "När ditt barn skapar ett konto online ska inte din information hamna i fel händer. Det är lätt att den säljs vidare i ett paket med 10 000 andra på en marknadsplats i dark web.",
                    "image": "Frame25.png"
                }
            },
            {
                "subtitle": "Ta ansvar!",
                "text": "Använd aldrig samma lösenord för flera tjänster, eftersom ett stulet lösenord kan öppna många dörrar. Starka och unika lösenord, gärna lagrade i en lösenordshanterare, gör det enklare att hålla koll. Aktivera alltid tvåfaktorsautentisering för ett extra skyddslager. Använd föräldrakontroll för att begränsa barnens tillgång till olämpligt innehåll. På så sätt kan du minska risken för informationsläckage och skydda både dig och ditt barn."
            }
        ],
        "quiz": [
            {
                "quizQuestion": "Ditt Lösenord är just nu Äpple123. Du ska göra ett nytt lösenord. Vilket alternativ är säkrast?",
                "quizOptions": [
                    {
                        "quizId": "option1",
                        "option": "Äpple321",
                        "correctAnswer": false
                    },
                    {
                        "quizId": "option2",
                        "option": "Päron987",
                        "correctAnswer": true
                    },
                    {
                        "quizId": "option3",
                        "option": "Äpple456",
                        "correctAnswer": false
                    },
                    {
                        "quizId": "option4",
                        "option": "Äpple123",
                        "correctAnswer": false
                    }
                ],
                "quizAnswer": "Päron987 är ett bra val - lätt att minnas men tillräckligt olikt det gamla lösenordet. Ett mer komplext lösenord, som J4gÄl5k:rHunDAr!?, hade varit säkrare, men är ofta svårare att komma ihåg. Det gäller att hitta en bra balans."
            },
            {
                "quizQuestion": "Vilken information får du ge ut till en främling online?",
                "quizOptions": [
                    {
                        "quizId": "option1",
                        "option": "Mejladress",
                        "correctAnswer": false
                    },
                    {
                        "quizId": "option2",
                        "option": "Lösenord",
                        "correctAnswer": false
                    },
                    {
                        "quizId": "option3",
                        "option": "Användarnamn",
                        "correctAnswer": true
                    },
                    {
                        "quizId": "option4",
                        "option": "Telefonnummer",
                        "correctAnswer": false
                    }
                ],
                "quizAnswer": "Användarnamnet är någonting som är offentligt och därigenom inte någonting som kan spåra dig (så vidare det inte består av personliga uppgifter). Du bör aldrig ge ut privat information till folk du inte känner."
            }
        ]
    },
    {
        "id": "1",
        "name": "Exempel 2",
        "time": "5",
        "age": "3-6",
        "content": [
            {
                "title": "Annan Titel",
                "text": "Den andra Lorem ipsum dolor sit amet, consectetur adipiscing elit. Ut et massa mi. Aliquam in hendrerit urna. Pellentesque sit amet sapien fringilla, mattis ligula consectetur, ultrices mauris. Maecenas vitae mattis tellus."
            },
            {
                "subtitle": "Undertitel",
                "text": "Lorem ipsum dolor sit amet, consectetur adipiscing elit. Ut et massa mi. Aliquam in hendrerit urna. Pellentesque sit amet sapien fringilla, mattis ligula consectetur, ultrices mauris. Maecenas vitae mattis tellus."
            }
        ]
    },
    {
        "id": "2",
        "name": "Exempel 3",
        "time": "7",
        "age": "3-6",
        "content": [
            {
                "title": "En tredje Titel",
                "text": "Lorem ipsum dolor sit amet, consectetur adipiscing elit. Ut et massa mi. Aliquam in hendrerit urna. Pellentesque sit amet sapien fringilla, mattis ligula consectetur, ultrices mauris. Maecenas vitae mattis tellus."
            }
        ]
    },
    {
        "id": "3",
        "name": "Exempel 6",
        "time": "2",
        "age": "3-6",
        "content": [
            {
                "title": "Exempel"
            }
        ]
    },
    {
        "id": "4",
        "name": "Exempel 2",
        "time": "2",
        "age": "7-10",
        "content": [
            {
                "title": "Exempel"
            }
        ]
    },
    {
        "id": "5",
        "name": "Exempel 2",
        "time": "2",
        "age": "7-10",
        "content": [
            {
                "title": "Exempel"
            }
        ]
    },
    {
        "id": "6",
        "name": "Exempel 2",
        "time": "2",
        "age": "7-10",
        "content": [
            {
                "title": "Exempel"
            }
        ]
    },
    {
        "id": "7",
        "name": "Exempel 2",
        "time": "2",
        "age": "7-10",
        "content": [
            {
                "title": "Exempel"
            }
        ]
    },
    {
        "id": "8",
        "name": "Vad är phishing",
        "time": "5",
        "imageUrl": "phishing.svg",
        "age": "11-14",
        "content": [
            {
                "title": "Vad är phishing - och varför drabbar det barn",
                "text": "Phishing, eller nätfiske, är när någon försöker lura till sig personlig information genom att låtsas vara någon annan. Det kan handla om att en bedragare skickar ett mejl, ett SMS eller ett meddelande i en app där de påstår sig representera en spelplattform, ett företag eller till och med en kompis. Målet är att få barnet att klicka på en länk, skriva in sitt lösenord, eller lämna ut känslig information."
            },
            {
                "text": "För barn som rör sig i spelvärldar, på sociala medier eller i appar där man kommunicerar med andra, är risken större än man kanske tror. Många bedragare riktar sig just mot yngre användare eftersom de är mer lättlurade och mindre benägna att ifrågasätta det de ser."
            },
            {
                "subtitle": "Hur kan phishing se ut för barn?",
                "text": "Phishing riktat mot barn tar ofta formen av något lockande eller hotfullt. Det kan vara ett meddelande som säger att barnet vunnit något - till exempel spelvaluta, skins eller ett exklusivt erbjudande. Eller så kan det handla om att någon låtsas vara administratör och påstår att barnets konto håller på att raderas om de inte loggar in igen 'omedelbart'."
            },
            {
                "text": "Föräldrar märker ibland inte när något hänt, eftersom barn ofta inte vågar berätta. Kanske för att de skäms, är rädda för att bli av med mobilen, eller helt enkelt inte förstår vad de har varit med om. Därför är det viktigt att du som vuxen har koll - och vågar prata om det som känns svårt."
            },
            {
                "subtitle": "Vad behöver barn veta - och hur pratar man om det?",
                "text": "Du behöver inte vara tekniskt kunnig för att göra stor skillnad. Det räcker ofta med enkla samtal i vardagen. Berätta att riktiga företag aldrig ber om lösenord via chatt. Förklara att det är bättre att fråga en vuxen en gång för mycket än en gång för lite. Och framför allt - gör klart att det inte är barnets fel om de blir lurade."
            },
            {
                "text": "Ett bra sätt att börja samtalet är att visa ett misstänkt SMS eller mejl du själv fått. Fråga vad barnet tycker verkar märkligt. Ser webbadressen konstig ut? Är språket dåligt? Låter det för bra för att vara sant? På så sätt bygger du en vana hos barnet att vara uppmärksam och ifrågasätta."
            },
            {
                "subtitle": "Vad kan du som förälder göra direkt?",
                "text": "Det finns flera enkla saker du kan göra idag för att minska risken för att ditt barn utsätts för phishing. Börja med att slå på tvåstegsverifiering på barnets viktiga konton - det är ett extra skydd om någon försöker ta sig in. Gå också igenom vilka appar barnet använder, och se till att ni tillsammans förstår hur de fungerar."
            },
            {
                "text": "Men det viktigaste är kanske ändå relationen. Ett barn som känner att det är okej att komma till dig - även när något gått fel - har ett betydligt bättre skydd än vilket virusprogram som helst. Du är inte bara en förälder, du är också barnets bästa brandvägg."
            },
            {
                "subtitle": "Sammanfattning",
                "text": "Phishing är en av de vanligaste hoten på nätet, och barn är en särskilt utsatt grupp. Genom att prata öppet, visa intresse och ge barnet strategier för att känna igen bedrägeriförsök, bygger du ett skydd som räcker långt. Det behöver inte vara komplicerat - men det kräver att du vågar vara nyfiken på vad som händer bakom skärmen."
            }
        ],
        "quiz": [
            {
                "quizQuestion": "Fråga 1",
                "quizOptions": [
                    {
                        "quizId": "option1",
                        "option": "Exempel1",
                        "correctAnswer": false
                    },
                    {
                        "quizId": "option2",
                        "option": "Exempel2",
                        "correctAnswer": true
                    },
                    {
                        "quizId": "option3",
                        "option": "Exempel3",
                        "correctAnswer": false
                    },
                    {
                        "quizId": "option4",
                        "option": "Exempel4",
                        "correctAnswer": false
                    }
                ],
                "quizAnswer": "Föräldrar märker ibland inte när något hänt, eftersom barn ofta inte vågar berätta. Kanske för att de skäms, är rädda för att bli av med mobilen, eller helt enkelt inte förstår vad de har varit med om. Därför är det viktigt att du som vuxen har koll - och vågar prata om det som känns svårt."
            },
            {
                "quizQuestion": "Fråga 2",
                "quizOptions": [
                    {
                        "quizId": "option1",
                        "option": "quiz2",
                        "correctAnswer": false
                    },
                    {
                        "quizId": "option2",
                        "option": "Exempel2",
                        "correctAnswer": true
                    },
                    {
                        "quizId": "option3",
                        "option": "Exempel3",
                        "correctAnswer": false
                    },
                    {
                        "quizId": "option4",
                        "option": "Exempel4",
                        "correctAnswer": false
                    }
                ],
                "quizAnswer": "Korrekt svar"
            }
        ]
    },
    {
        "id": "9",
        "name": "Exempel 11",
        "time": "2",
        "age": "15-17",
        "content": [
            {
                "title": "Vad är phishing - och varför drabbar det barn",
                "text": "Phishing, eller nätfiske, är när någon försöker lura till sig personlig information genom att låtsas vara någon annan. Det kan handla om att en bedragare skickar ett mejl, ett SMS eller ett meddelande i en app där de påstår sig representera en spelplattform, ett företag eller till och med en kompis. Målet är att få barnet att klicka på en länk, skriva in sitt lösenord, eller lämna ut känslig information."
            },
            {
                "text": "För barn som rör sig i spelvärldar, på sociala medier eller i appar där man kommunicerar med andra, är risken större än man kanske tror. Många bedragare riktar sig just mot yngre användare eftersom de är mer lättlurade och mindre benägna att ifrågasätta det de ser."
            },
            {
                "subtitle": "Hur kan phishing se ut för barn?",
                "text": "Phishing riktat mot barn tar ofta formen av något lockande eller hotfullt. Det kan vara ett meddelande som säger att barnet vunnit något - till exempel spelvaluta, skins eller ett exklusivt erbjudande. Eller så kan det handla om att någon låtsas vara administratör och påstår att barnets konto håller på att raderas om de inte loggar in igen 'omedelbart'."
            },
            {
                "text": "Föräldrar märker ibland inte när något hänt, eftersom barn ofta inte vågar berätta. Kanske för att de skäms, är rädda för att bli av med mobilen, eller helt enkelt inte förstår vad de har varit med om. Därför är det viktigt att du som vuxen har koll - och vågar prata om det som känns svårt."
            },
            {
                "subtitle": "Vad behöver barn veta - och hur pratar man om det?",
                "text": "Du behöver inte vara tekniskt kunnig för att göra stor skillnad. Det räcker ofta med enkla samtal i vardagen. Berätta att riktiga företag aldrig ber om lösenord via chatt. Förklara att det är bättre att fråga en vuxen en gång för mycket än en gång för lite. Och framför allt - gör klart att det inte är barnets fel om de blir lurade."
            },
            {
                "text": "Ett bra sätt att börja samtalet är att visa ett misstänkt SMS eller mejl du själv fått. Fråga vad barnet tycker verkar märkligt. Ser webbadressen konstig ut? Är språket dåligt? Låter det för bra för att vara sant? På så sätt bygger du en vana hos barnet att vara uppmärksam och ifrågasätta."
            },
            {
                "subtitle": "Vad kan du som förälder göra direkt?",
                "text": "Det finns flera enkla saker du kan göra idag för att minska risken för att ditt barn utsätts för phishing. Börja med att slå på tvåstegsverifiering på barnets viktiga konton - det är ett extra skydd om någon försöker ta sig in. Gå också igenom vilka appar barnet använder, och se till att ni tillsammans förstår hur de fungerar."
            },
            {
                "text": "Men det viktigaste är kanske ändå relationen. Ett barn som känner att det är okej att komma till dig - även när något gått fel - har ett betydligt bättre skydd än vilket virusprogram som helst. Du är inte bara en förälder, du är också barnets bästa brandvägg."
            },
            {
                "subtitle": "Sammanfattning",
                "text": "Phishing är en av de vanligaste hoten på nätet, och barn är en särskilt utsatt grupp. Genom att prata öppet, visa intresse och ge barnet strategier för att känna igen bedrägeriförsök, bygger du ett skydd som räcker långt. Det behöver inte vara komplicerat - men det kräver att du vågar vara nyfiken på vad som händer bakom skärmen."
            },
            {
                "text": "Föräldrar märker ibland inte när något hänt, eftersom barn ofta inte vågar berätta. Kanske för att de skäms, är rädda för att bli av med mobilen, eller helt enkelt inte förstår vad de har varit med om. Därför är det viktigt att du som vuxen har koll - och vågar prata om det som känns svårt."
            }
        ],
        "quiz": [
            {
                "quizQuestion": "Fråga 1",
                "quizOptions": [
                    {
                        "quizId": "option1",
                        "option": "Exempel1",
                        "correctAnswer": false
                    },
                    {
                        "quizId": "option2",
                        "option": "Exempel2",
                        "correctAnswer": true
                    },
                    {
                        "quizId": "option3",
                        "option": "Exempel3",
                        "correctAnswer": false
                    },
                    {
                        "quizId": "option4",
                        "option": "Exempel4",
                        "correctAnswer": false
                    }
                ],
                "quizAnswer": "Föräldrar märker ibland inte när något hänt, eftersom barn ofta inte vågar berätta. Kanske för att de skäms, är rädda för att bli av med mobilen, eller helt enkelt inte förstår vad de har varit med om. Därför är det viktigt att du som vuxen har koll - och vågar prata om det som känns svårt."
            },
            {
                "quizQuestion": "Fråga 2",
                "quizOptions": [
                    {
                        "quizId": "option1",
                        "option": "quiz2",
                        "correctAnswer": false
                    },
                    {
                        "quizId": "option2",
                        "option": "Exempel2",
                        "correctAnswer": true
                    },
                    {
                        "quizId": "option3",
                        "option": "Exempel3",
                        "correctAnswer": false
                    },
                    {
                        "quizId": "option4",
                        "option": "Exempel4",
                        "correctAnswer": false
                    }
                ],
                "quizAnswer": "Korrekt svar"
            }
        ]
    }
]